avrocurio/__init__.py
avrocurio/config.py
avrocurio/exceptions.py
avrocurio/py.typed
avrocurio/schema_client.py
avrocurio/serializer.py
avrocurio/wire_format.py
avrocurio-1.1.0.dist-info/METADATA
avrocurio-1.1.0.dist-info/WHEEL
avrocurio-1.1.0.dist-info/licenses/LICENSE
avrocurio-1.1.0.dist-info/RECORD
