Metadata-Version: 2.4
Name: avrocurio
Version: 1.1.0
Summary: Apache Avro serialization/deserialization with Confluent Schema Registry framing and Apicurio integration
Project-URL: source, https://github.com/castoredc/avrocurio/
Project-URL: changelog, https://github.com/castoredc/avrocurio/blob/main/CHANGELOG.md
Author-email: Castor <dev@castoredc.com>
Maintainer-email: Nick Groenen <nick.groenen@castoredc.com>
License-Expression: BSD-2-Clause-Patent
License-File: LICENSE
Requires-Python: >=3.11
Requires-Dist: cachetools>=5.0.0
Requires-Dist: dataclasses-avroschema>=0.62.0
Requires-Dist: fastavro>=1.9.0
Requires-Dist: httpx>=0.27.0
Requires-Dist: typing-extensions>=4.0.0
